agentpipe/__init__.py
agentpipe/context.py
agentpipe/format.py
agentpipe/runnable.py
agentpipe/tasks.py
agentpipe/tools.py
agentpipe-0.1.0.dist-info/METADATA
agentpipe-0.1.0.dist-info/WHEEL
agentpipe-0.1.0.dist-info/top_level.txt
agentpipe-0.1.0.dist-info/RECORD
