Metadata-Version: 2.4
Name: agentpipe
Version: 0.1.0
Summary: A minimal, composable library for building LLM-powered agents and pipes.
Home-page: https://github.com/koenvaneijk/agentpipe
Author: Koen van Eijk
Author-email: vaneijk.koen@gmail.com
License: MIT
Classifier: Programming Language :: Python :: 3
Classifier: License :: OSI Approved :: MIT License
Classifier: Operating System :: OS Independent
Classifier: Intended Audience :: Developers
Classifier: Topic :: Scientific/Engineering :: Artificial Intelligence
Requires-Python: >=3.8
Requires-Dist: zenllm
Requires-Dist: Jinja2
Requires-Dist: pydantic
Dynamic: author
Dynamic: author-email
Dynamic: classifier
Dynamic: description
Dynamic: description-content-type
Dynamic: home-page
Dynamic: license
Dynamic: requires-dist
Dynamic: requires-python
Dynamic: summary
